ndx_extract/__init__.py
ndx_extract/extract.py
ndx_extract/spec/ndx-extract.extensions.yaml
ndx_extract/spec/ndx-extract.namespace.yaml
ndx_extract-0.2.0.dist-info/LICENSE
ndx_extract-0.2.0.dist-info/METADATA
ndx_extract-0.2.0.dist-info/WHEEL
ndx_extract-0.2.0.dist-info/top_level.txt
ndx_extract-0.2.0.dist-info/RECORD
