Metadata-Version: 2.1
Name: ndx-extract
Version: 0.2.0
Summary: NWB extension for storage of parameters and output of EXTRACT pipeline.
Home-page: https://github.com/catalystneuro/ndx-extract
Author: Ben Dichter, Szonja Weigl and Cesar Echavarria
Author-email: ben.dichter@catalystneuro.com
License: BSD 3-Clause
Classifier: Intended Audience :: Developers
Classifier: Intended Audience :: Science/Research
License-File: LICENSE
Requires-Dist: pynwb (<3,>=1.5.0)
Requires-Dist: hdmf (<4,>=2.5.6)
Requires-Dist: hdmf-docutils (<1,>=0.4.4)
